{
  "GroupName": "MainMission8002105_",
  "Category": "Mission",
  "ConfigPrefabPath": null,
  "LevelGraph": null,
  "AreaAnchorName": "LevelArea_P20123_F20123001_G99",
  "SaveType": "Reset",
  "LoadCondition": null,
  "UnloadCondition": null,
  "ForceUnloadCondition": null,
  "SavedValueCondition": null,
  "SystemUnlockCondition": null,
  "AtmosphereCondition": null,
  "UseCustomSaveData": false,
  "IsPendedLoad": false,
  "IsPendedUnload": false,
  "LoadSide": "Client",
  "LoadOnInitial": false,
  "OwnerMainMissionID": 8002105,
  "AirlineInitPrefabPaths": null,
  "RandomInit": null,
  "GroupStateList": null,
  "GroupRefreshID": 0,
  "ValueSource": {
    "Values": null,
    "SharedValues": null
  },
  "ConflictIDList": [],
  "IsHoyoGroup": false,
  "HoYoGroupType": "Standard",
  "StreamingTemplateType": "Standard",
  "ConflictWhiteList": null,
  "EnableGroupAI": false,
  "TagContainer": null,
  "IsSaveNeedMergeBack": false,
  "AnchorList": [
    {
      "RotX": 0.0,
      "RotZ": 0.0,
      "Usage": "Unspecified",
      "LookAtCameraTemplate": null,
      "CustomParameter": null,
      "Name": "Anchor1",
      "RotY": 0.0,
      "ID": 1,
      "PosX": 27.46,
      "PosY": 19.97829,
      "PosZ": -52.52,
      "IsDelete": false
    }
  ],
  "MonsterList": [],
  "PropList": [
    {
      "RotX": 0.0,
      "RotZ": 0.0,
      "Scale": {
        "x": 5.0,
        "y": 5.0,
        "z": 5.0,
        "IsNaN": false,
        "IsInfinity": false,
        "IsPositiveInfinity": false,
        "IsNegativeInfinity": false,
        "normalized": {
          "x": 0.577350259,
          "y": 0.577350259,
          "z": 0.577350259,
          "IsNaN": false,
          "IsInfinity": false,
          "IsPositiveInfinity": false,
          "IsNegativeInfinity": false,
          "normalized": {
            "x": 0.5773503,
            "y": 0.5773503,
            "z": 0.5773503,
            "IsNaN": false,
            "IsInfinity": false,
            "IsPositiveInfinity": false,
            "IsNegativeInfinity": false,
            "magnitude": 1.00000012,
            "sqrMagnitude": 1.00000024
          },
          "magnitude": 0.99999994,
          "sqrMagnitude": 0.99999994
        },
        "magnitude": 8.66025448,
        "sqrMagnitude": 75.0
      },
      "PropID": 121,
      "LoadOnInitial": false,
      "IsOverrideInitLevelGraph": true,
      "InitLevelGraph": null,
      "ValueSource": {
        "Values": null,
        "SharedValues": null
      },
      "Trigger": null,
      "CampID": 4,
      "State": "Closed",
      "EventID": 0,
      "OverrideHintRange": -1.0,
      "OverrideSoundRange": -1.0,
      "CustomTriggerMap": {},
      "CustomTriggerMapV2": {},
      "BridgeStateRotations": [],
      "StateConfigs": null,
      "AnchorGroupID": 0,
      "AnchorID": 0,
      "ChestID": 0,
      "MappingInfoID": 0,
      "SubMapID": 0,
      "DialogueTriggerAngle": 120,
      "DialogueGroups": [],
      "FirstDialogueGroupID": 0,
      "TalkDialogGroupIDList": [],
      "TalkChosenType": "undefined",
      "ServerInteractVerificationIDList": [],
      "HideInCutScene": false,
      "HideInStory": false,
      "PerformanceHideFlags": 0,
      "DisableDither": false,
      "StageObjectCapture": null,
      "RaidID": 0,
      "FarmElementID": 0,
      "CocoonID": 0,
      "ActivityMapConditionIDList": null,
      "OverrideMapIconType": -1,
      "OverrideMapStateIcons": null,
      "OverridePropName": {
        "hash": 371857150
      },
      "Dialog": null,
      "InteractIconType": "ChatMissionIcon",
      "DialogueTriggerSkipFakeAvatar": true,
      "DialogueTriggerSkipSpecifiedFakeAvatarList": null,
      "InteractTitle": {
        "hash": 371857150
      },
      "CustomParameter": null,
      "MapCustomParameter": null,
      "NearestTeleportMappingInfoID": 0,
      "OverrideBoardShowList": null,
      "IsClientOnly": false,
      "OverrideTriggerValidGuestConfig": false,
      "TriggerValidGuest": null,
      "TagOverrideConfig": null,
      "TagOverrideComponents": null,
      "CameraCollisionPoint": {
        "x": 0.0,
        "y": 0.0,
        "z": 0.0,
        "IsNaN": false,
        "IsInfinity": false,
        "IsPositiveInfinity": false,
        "IsNegativeInfinity": false,
        "magnitude": 0.0,
        "sqrMagnitude": 0.0
      },
      "CameraCenterEntityList": null,
      "CameraConfig": null,
      "IsOverrideAudioSwitch": false,
      "AudioSwitchGroupName": null,
      "AudioSwitchName": null,
      "OverrideReplaceMaterialKey": null,
      "SoundProfileOverrideID": 0,
      "LookAtPlayer": false,
      "LookAtPlayerTriggerRadius": 2.0,
      "IsOverrideLockRaycastOffset": false,
      "OverrideLockRaycastOffset": 1.5,
      "SpawnConfig": null,
      "Name": "Prop1",
      "RotY": 0.0,
      "ID": 300001,
      "PosX": 57.93,
      "PosY": 18.5,
      "PosZ": -7.46,
      "IsDelete": false
    },
    {
      "RotX": 0.0,
      "RotZ": 0.0,
      "Scale": {
        "x": 12.0,
        "y": 15.0,
        "z": 12.0,
        "IsNaN": false,
        "IsInfinity": false,
        "IsPositiveInfinity": false,
        "IsNegativeInfinity": false,
        "normalized": {
          "x": 0.529812932,
          "y": 0.6622662,
          "z": 0.529812932,
          "IsNaN": false,
          "IsInfinity": false,
          "IsPositiveInfinity": false,
          "IsNegativeInfinity": false,
          "magnitude": 1.0,
          "sqrMagnitude": 1.0
        },
        "magnitude": 22.6495037,
        "sqrMagnitude": 513.0
      },
      "PropID": 121,
      "LoadOnInitial": false,
      "IsOverrideInitLevelGraph": true,
      "InitLevelGraph": null,
      "ValueSource": {
        "Values": null,
        "SharedValues": null
      },
      "Trigger": null,
      "CampID": 4,
      "State": "Closed",
      "EventID": 0,
      "OverrideHintRange": -1.0,
      "OverrideSoundRange": -1.0,
      "CustomTriggerMap": {},
      "CustomTriggerMapV2": {},
      "BridgeStateRotations": [],
      "StateConfigs": null,
      "AnchorGroupID": 0,
      "AnchorID": 0,
      "ChestID": 0,
      "MappingInfoID": 0,
      "SubMapID": 0,
      "DialogueTriggerAngle": 120,
      "DialogueGroups": [],
      "FirstDialogueGroupID": 0,
      "TalkDialogGroupIDList": [],
      "TalkChosenType": "undefined",
      "ServerInteractVerificationIDList": [],
      "HideInCutScene": false,
      "HideInStory": false,
      "PerformanceHideFlags": 0,
      "DisableDither": false,
      "StageObjectCapture": null,
      "RaidID": 0,
      "FarmElementID": 0,
      "CocoonID": 0,
      "ActivityMapConditionIDList": null,
      "OverrideMapIconType": -1,
      "OverrideMapStateIcons": null,
      "OverridePropName": {
        "hash": 371857150
      },
      "Dialog": null,
      "InteractIconType": "ChatMissionIcon",
      "DialogueTriggerSkipFakeAvatar": true,
      "DialogueTriggerSkipSpecifiedFakeAvatarList": null,
      "InteractTitle": {
        "hash": 371857150
      },
      "CustomParameter": null,
      "MapCustomParameter": null,
      "NearestTeleportMappingInfoID": 0,
      "OverrideBoardShowList": null,
      "IsClientOnly": false,
      "OverrideTriggerValidGuestConfig": false,
      "TriggerValidGuest": null,
      "TagOverrideConfig": null,
      "TagOverrideComponents": null,
      "CameraCollisionPoint": {
        "x": 0.0,
        "y": 0.0,
        "z": 0.0,
        "IsNaN": false,
        "IsInfinity": false,
        "IsPositiveInfinity": false,
        "IsNegativeInfinity": false,
        "magnitude": 0.0,
        "sqrMagnitude": 0.0
      },
      "CameraCenterEntityList": null,
      "CameraConfig": null,
      "IsOverrideAudioSwitch": false,
      "AudioSwitchGroupName": null,
      "AudioSwitchName": null,
      "OverrideReplaceMaterialKey": null,
      "SoundProfileOverrideID": 0,
      "LookAtPlayer": false,
      "LookAtPlayerTriggerRadius": 2.0,
      "IsOverrideLockRaycastOffset": false,
      "OverrideLockRaycastOffset": 1.5,
      "SpawnConfig": null,
      "Name": "Prop2",
      "RotY": 0.0,
      "ID": 300002,
      "PosX": 56.07,
      "PosY": 31.14,
      "PosZ": -82.19,
      "IsDelete": false
    },
    {
      "RotX": 0.0,
      "RotZ": 0.0,
      "Scale": {
        "x": 10.0,
        "y": 10.0,
        "z": 10.0,
        "IsNaN": false,
        "IsInfinity": false,
        "IsPositiveInfinity": false,
        "IsNegativeInfinity": false,
        "normalized": {
          "x": 0.577350259,
          "y": 0.577350259,
          "z": 0.577350259,
          "IsNaN": false,
          "IsInfinity": false,
          "IsPositiveInfinity": false,
          "IsNegativeInfinity": false,
          "normalized": {
            "x": 0.5773503,
            "y": 0.5773503,
            "z": 0.5773503,
            "IsNaN": false,
            "IsInfinity": false,
            "IsPositiveInfinity": false,
            "IsNegativeInfinity": false,
            "magnitude": 1.00000012,
            "sqrMagnitude": 1.00000024
          },
          "magnitude": 0.99999994,
          "sqrMagnitude": 0.99999994
        },
        "magnitude": 17.320509,
        "sqrMagnitude": 300.0
      },
      "PropID": 121,
      "LoadOnInitial": false,
      "IsOverrideInitLevelGraph": true,
      "InitLevelGraph": null,
      "ValueSource": {
        "Values": null,
        "SharedValues": null
      },
      "Trigger": null,
      "CampID": 4,
      "State": "Closed",
      "EventID": 0,
      "OverrideHintRange": -1.0,
      "OverrideSoundRange": -1.0,
      "CustomTriggerMap": {},
      "CustomTriggerMapV2": {},
      "BridgeStateRotations": [],
      "StateConfigs": null,
      "AnchorGroupID": 0,
      "AnchorID": 0,
      "ChestID": 0,
      "MappingInfoID": 0,
      "SubMapID": 0,
      "DialogueTriggerAngle": 120,
      "DialogueGroups": [],
      "FirstDialogueGroupID": 0,
      "TalkDialogGroupIDList": [],
      "TalkChosenType": "undefined",
      "ServerInteractVerificationIDList": [],
      "HideInCutScene": false,
      "HideInStory": false,
      "PerformanceHideFlags": 0,
      "DisableDither": false,
      "StageObjectCapture": null,
      "RaidID": 0,
      "FarmElementID": 0,
      "CocoonID": 0,
      "ActivityMapConditionIDList": null,
      "OverrideMapIconType": -1,
      "OverrideMapStateIcons": null,
      "OverridePropName": {
        "hash": 371857150
      },
      "Dialog": null,
      "InteractIconType": "ChatMissionIcon",
      "DialogueTriggerSkipFakeAvatar": true,
      "DialogueTriggerSkipSpecifiedFakeAvatarList": null,
      "InteractTitle": {
        "hash": 371857150
      },
      "CustomParameter": null,
      "MapCustomParameter": null,
      "NearestTeleportMappingInfoID": 0,
      "OverrideBoardShowList": null,
      "IsClientOnly": false,
      "OverrideTriggerValidGuestConfig": false,
      "TriggerValidGuest": null,
      "TagOverrideConfig": null,
      "TagOverrideComponents": null,
      "CameraCollisionPoint": {
        "x": 0.0,
        "y": 0.0,
        "z": 0.0,
        "IsNaN": false,
        "IsInfinity": false,
        "IsPositiveInfinity": false,
        "IsNegativeInfinity": false,
        "magnitude": 0.0,
        "sqrMagnitude": 0.0
      },
      "CameraCenterEntityList": null,
      "CameraConfig": null,
      "IsOverrideAudioSwitch": false,
      "AudioSwitchGroupName": null,
      "AudioSwitchName": null,
      "OverrideReplaceMaterialKey": null,
      "SoundProfileOverrideID": 0,
      "LookAtPlayer": false,
      "LookAtPlayerTriggerRadius": 2.0,
      "IsOverrideLockRaycastOffset": false,
      "OverrideLockRaycastOffset": 1.5,
      "SpawnConfig": null,
      "Name": "Prop3",
      "RotY": 0.0,
      "ID": 300003,
      "PosX": 43.2,
      "PosY": 39.78,
      "PosZ": -85.35,
      "IsDelete": false
    },
    {
      "RotX": 0.0,
      "RotZ": 0.0,
      "Scale": {
        "x": 12.0,
        "y": 17.0,
        "z": 10.0,
        "IsNaN": false,
        "IsInfinity": false,
        "IsPositiveInfinity": false,
        "IsNegativeInfinity": false,
        "normalized": {
          "x": 0.5197777,
          "y": 0.7363518,
          "z": 0.4331481,
          "IsNaN": false,
          "IsInfinity": false,
          "IsPositiveInfinity": false,
          "IsNegativeInfinity": false,
          "magnitude": 1.0,
          "sqrMagnitude": 1.00000012
        },
        "magnitude": 23.086792,
        "sqrMagnitude": 533.0
      },
      "PropID": 121,
      "LoadOnInitial": false,
      "IsOverrideInitLevelGraph": true,
      "InitLevelGraph": null,
      "ValueSource": {
        "Values": null,
        "SharedValues": null
      },
      "Trigger": null,
      "CampID": 4,
      "State": "Closed",
      "EventID": 0,
      "OverrideHintRange": -1.0,
      "OverrideSoundRange": -1.0,
      "CustomTriggerMap": {},
      "CustomTriggerMapV2": {},
      "BridgeStateRotations": [],
      "StateConfigs": null,
      "AnchorGroupID": 0,
      "AnchorID": 0,
      "ChestID": 0,
      "MappingInfoID": 0,
      "SubMapID": 0,
      "DialogueTriggerAngle": 120,
      "DialogueGroups": [],
      "FirstDialogueGroupID": 0,
      "TalkDialogGroupIDList": [],
      "TalkChosenType": "undefined",
      "ServerInteractVerificationIDList": [],
      "HideInCutScene": false,
      "HideInStory": false,
      "PerformanceHideFlags": 0,
      "DisableDither": false,
      "StageObjectCapture": null,
      "RaidID": 0,
      "FarmElementID": 0,
      "CocoonID": 0,
      "ActivityMapConditionIDList": null,
      "OverrideMapIconType": -1,
      "OverrideMapStateIcons": null,
      "OverridePropName": {
        "hash": 371857150
      },
      "Dialog": null,
      "InteractIconType": "ChatMissionIcon",
      "DialogueTriggerSkipFakeAvatar": true,
      "DialogueTriggerSkipSpecifiedFakeAvatarList": null,
      "InteractTitle": {
        "hash": 371857150
      },
      "CustomParameter": null,
      "MapCustomParameter": null,
      "NearestTeleportMappingInfoID": 0,
      "OverrideBoardShowList": null,
      "IsClientOnly": false,
      "OverrideTriggerValidGuestConfig": false,
      "TriggerValidGuest": null,
      "TagOverrideConfig": null,
      "TagOverrideComponents": null,
      "CameraCollisionPoint": {
        "x": 0.0,
        "y": 0.0,
        "z": 0.0,
        "IsNaN": false,
        "IsInfinity": false,
        "IsPositiveInfinity": false,
        "IsNegativeInfinity": false,
        "magnitude": 0.0,
        "sqrMagnitude": 0.0
      },
      "CameraCenterEntityList": null,
      "CameraConfig": null,
      "IsOverrideAudioSwitch": false,
      "AudioSwitchGroupName": null,
      "AudioSwitchName": null,
      "OverrideReplaceMaterialKey": null,
      "SoundProfileOverrideID": 0,
      "LookAtPlayer": false,
      "LookAtPlayerTriggerRadius": 2.0,
      "IsOverrideLockRaycastOffset": false,
      "OverrideLockRaycastOffset": 1.5,
      "SpawnConfig": null,
      "Name": "Prop4",
      "RotY": 0.0,
      "ID": 300004,
      "PosX": 63.69,
      "PosY": 32.51,
      "PosZ": -70.73,
      "IsDelete": false
    }
  ],
  "DistrictList": [],
  "WaypointList": [],
  "PathwayList": [],
  "BattleAreaList": [],
  "NPCList": [],
  "CrowdList": [],
  "PedestrianList": [],
  "PedestrianV2List": null,
  "AudienceList": null,
  "SmartObjectList": [],
  "CurveList": null,
  "LittleGameList": null
}