{
  "GroupName": "MainMission2000802_8",
  "Category": "Mission",
  "ConfigPrefabPath": null,
  "LevelGraph": null,
  "AreaAnchorName": "LevelArea_P43001_F43001001_G22",
  "SaveType": "Reset",
  "LoadCondition": {
    "Conditions": [
      {
        "Type": "SubMission",
        "Phase": "Accept",
        "ID": 200080255
      }
    ],
    "Operation": "And",
    "DelayToLevelReload": false
  },
  "UnloadCondition": {
    "Conditions": [
      {
        "Type": "SubMission",
        "Phase": "Finish",
        "ID": 200080255
      }
    ],
    "Operation": "And",
    "DelayToLevelReload": false
  },
  "ForceUnloadCondition": null,
  "SavedValueCondition": null,
  "SystemUnlockCondition": null,
  "AtmosphereCondition": null,
  "UseCustomSaveData": false,
  "IsPendedLoad": false,
  "IsPendedUnload": false,
  "LoadSide": "Client",
  "LoadOnInitial": false,
  "OwnerMainMissionID": 2000802,
  "AirlineInitPrefabPaths": null,
  "RandomInit": null,
  "GroupStateList": null,
  "GroupRefreshID": 0,
  "ValueSource": {
    "Values": null,
    "SharedValues": null
  },
  "ConflictIDList": [],
  "IsHoyoGroup": false,
  "HoYoGroupType": "Standard",
  "StreamingTemplateType": "Standard",
  "ConflictWhiteList": null,
  "EnableGroupAI": false,
  "TagContainer": null,
  "IsSaveNeedMergeBack": false,
  "AnchorList": [
    {
      "RotX": 0.0,
      "RotZ": 0.0,
      "Usage": "Actor",
      "LookAtCameraTemplate": null,
      "CustomParameter": null,
      "Name": "Anchor1",
      "RotY": 190.0291,
      "ID": 1,
      "PosX": -2.948,
      "PosY": -4E-06,
      "PosZ": -1.11,
      "IsDelete": false
    },
    {
      "RotX": 5.473234,
      "RotZ": 0.405097,
      "Usage": "Camera",
      "LookAtCameraTemplate": null,
      "CustomParameter": {
        "fov": 27.0
      },
      "Name": "Anchor2",
      "RotY": 243.0634,
      "ID": 2,
      "PosX": -0.571,
      "PosY": 1.569,
      "PosZ": -0.39,
      "IsDelete": false
    }
  ],
  "MonsterList": [],
  "PropList": [],
  "DistrictList": [],
  "WaypointList": [],
  "PathwayList": [],
  "BattleAreaList": [],
  "NPCList": [
    {
      "RotX": 0.0,
      "RotZ": 0.0,
      "NPCID": 1004,
      "LevelGraph": null,
      "LoadOnInitial": false,
      "ValueSource": {
        "Values": null,
        "SharedValues": null
      },
      "CampID": 0,
      "UseDistrictTriggerType": false,
      "Trigger": null,
      "AIConfig": null,
      "AIVariableSource": null,
      "SOConfig": null,
      "StaticNPC": false,
      "OverrideLodTemplate": "WithoutLod",
      "DialogueTriggerAngle": 120,
      "DialogueGroups": [],
      "ServerInteractVerificationIDList": [],
      "IsOverrideArtModelOffset": false,
      "OverrideArtModelOffset": {
        "x": 0.0,
        "y": 0.0,
        "z": 0.0,
        "IsNaN": false,
        "IsInfinity": false,
        "IsPositiveInfinity": false,
        "IsNegativeInfinity": false,
        "magnitude": 0.0,
        "sqrMagnitude": 0.0
      },
      "DefaultIdleStateName": null,
      "DefaultBlendShapeConfigName": null,
      "BoneEmotionName": null,
      "IsOverrideAtlasEmotion": false,
      "OverrideAtlasEmotion": null,
      "DefaultLookAtMode": "LookPlayer",
      "DefaultLookAtTargetInfo": null,
      "DefaultLookAtPositionInfo": null,
      "MappingInfoID": 0,
      "SubMapID": 0,
      "OverrideTriggerSound": false,
      "SoundRange": 0.0,
      "NPCLodType": "Normal",
      "PossessionConfig": null,
      "BoardShowList": [],
      "OverrideNPCName": {
        "hash": 371857150
      },
      "OverrideNPCTitle": {
        "hash": 371857150
      },
      "DefaultStory": null,
      "FirstDialogueGroupID": 0,
      "TalkChosenType": "undefined",
      "TalkDialogGroupIDList": [],
      "DefaultAnimationType": "FreeStyle",
      "DefaultIdleFreeStyleMotionID": 310040000,
      "FreeStyleAnimGraphName": null,
      "OverrideSeriesID": 0,
      "IsMapContent": false,
      "MiniMapIconType": 0,
      "BornType": "Mission",
      "IsNeedFade": false,
      "IsInitialHidden": false,
      "InitialHiddenNodeList": [],
      "Dialog": null,
      "InteractIconType": "ChatIcon",
      "DialogueTriggerSkipFakeAvatar": true,
      "DialogueTriggerSkipSpecifiedFakeAvatarList": null,
      "OverrideBehaviorType": "None",
      "OverrideBehaviorParameter": null,
      "OverrideReplaceMaterialKeyList": null,
      "NearestTeleportMappingInfoID": 0,
      "RaidID": 0,
      "ActivityMapConditionIDList": null,
      "CameraCollisionPoint": {
        "x": 0.0,
        "y": 0.0,
        "z": 0.0,
        "IsNaN": false,
        "IsInfinity": false,
        "IsPositiveInfinity": false,
        "IsNegativeInfinity": false,
        "magnitude": 0.0,
        "sqrMagnitude": 0.0
      },
      "CameraCenterEntityList": null,
      "CameraConfig": null,
      "SFXOnLoad": null,
      "SpawnConfig": {
        "TryCapture": true,
        "CaptureDistanceTolerance": 1.5,
        "OverrideSpawn": false,
        "EntitySpawnConfig": {
          "NeedBlackIn": true,
          "BlackInDistance": 25.0,
          "NeedFadeIn": true,
          "NeedFadeOut": true
        }
      },
      "IsClientOnly": false,
      "OverrideTriggerValidGuestConfig": false,
      "TriggerValidGuest": {
        "ConfigType": "ByEntityType",
        "Npc": false,
        "NpcMonster": false,
        "LocalPlayer": true,
        "Teammember": true,
        "FakePlayer": false,
        "TargetList": null,
        "EvaluatedInstances": null
      },
      "Name": "NPC1",
      "RotY": 0.165045,
      "ID": 400001,
      "PosX": -3.058,
      "PosY": -5E-06,
      "PosZ": -2.47,
      "IsDelete": false
    },
    {
      "RotX": 0.0,
      "RotZ": 0.0,
      "NPCID": 1001,
      "LevelGraph": null,
      "LoadOnInitial": false,
      "ValueSource": {
        "Values": null,
        "SharedValues": null
      },
      "CampID": 0,
      "UseDistrictTriggerType": false,
      "Trigger": null,
      "AIConfig": null,
      "AIVariableSource": null,
      "SOConfig": null,
      "StaticNPC": false,
      "OverrideLodTemplate": "WithoutLod",
      "DialogueTriggerAngle": 120,
      "DialogueGroups": [],
      "ServerInteractVerificationIDList": [],
      "IsOverrideArtModelOffset": false,
      "OverrideArtModelOffset": {
        "x": 0.0,
        "y": 0.0,
        "z": 0.0,
        "IsNaN": false,
        "IsInfinity": false,
        "IsPositiveInfinity": false,
        "IsNegativeInfinity": false,
        "magnitude": 0.0,
        "sqrMagnitude": 0.0
      },
      "DefaultIdleStateName": null,
      "DefaultBlendShapeConfigName": null,
      "BoneEmotionName": null,
      "IsOverrideAtlasEmotion": false,
      "OverrideAtlasEmotion": null,
      "DefaultLookAtMode": "LookPlayer",
      "DefaultLookAtTargetInfo": null,
      "DefaultLookAtPositionInfo": null,
      "MappingInfoID": 0,
      "SubMapID": 0,
      "OverrideTriggerSound": false,
      "SoundRange": 0.0,
      "NPCLodType": "Normal",
      "PossessionConfig": null,
      "BoardShowList": [],
      "OverrideNPCName": {
        "hash": 371857150
      },
      "OverrideNPCTitle": {
        "hash": 371857150
      },
      "DefaultStory": null,
      "FirstDialogueGroupID": 0,
      "TalkChosenType": "undefined",
      "TalkDialogGroupIDList": [],
      "DefaultAnimationType": "FreeStyle",
      "DefaultIdleFreeStyleMotionID": 310010000,
      "FreeStyleAnimGraphName": null,
      "OverrideSeriesID": 0,
      "IsMapContent": false,
      "MiniMapIconType": 0,
      "BornType": "Mission",
      "IsNeedFade": false,
      "IsInitialHidden": false,
      "InitialHiddenNodeList": [],
      "Dialog": null,
      "InteractIconType": "ChatIcon",
      "DialogueTriggerSkipFakeAvatar": true,
      "DialogueTriggerSkipSpecifiedFakeAvatarList": null,
      "OverrideBehaviorType": "None",
      "OverrideBehaviorParameter": null,
      "OverrideReplaceMaterialKeyList": null,
      "NearestTeleportMappingInfoID": 0,
      "RaidID": 0,
      "ActivityMapConditionIDList": null,
      "CameraCollisionPoint": {
        "x": 0.0,
        "y": 0.0,
        "z": 0.0,
        "IsNaN": false,
        "IsInfinity": false,
        "IsPositiveInfinity": false,
        "IsNegativeInfinity": false,
        "magnitude": 0.0,
        "sqrMagnitude": 0.0
      },
      "CameraCenterEntityList": null,
      "CameraConfig": null,
      "SFXOnLoad": null,
      "SpawnConfig": {
        "TryCapture": true,
        "CaptureDistanceTolerance": 1.5,
        "OverrideSpawn": false,
        "EntitySpawnConfig": {
          "NeedBlackIn": true,
          "BlackInDistance": 25.0,
          "NeedFadeIn": true,
          "NeedFadeOut": true
        }
      },
      "IsClientOnly": false,
      "OverrideTriggerValidGuestConfig": false,
      "TriggerValidGuest": {
        "ConfigType": "ByEntityType",
        "Npc": false,
        "NpcMonster": false,
        "LocalPlayer": true,
        "Teammember": true,
        "FakePlayer": false,
        "TargetList": null,
        "EvaluatedInstances": null
      },
      "Name": "NPC4",
      "RotY": 142.6223,
      "ID": 400004,
      "PosX": -3.844,
      "PosY": -4E-06,
      "PosZ": -0.944,
      "IsDelete": false
    },
    {
      "RotX": 0.0,
      "RotZ": 0.0,
      "NPCID": 1302,
      "LevelGraph": null,
      "LoadOnInitial": false,
      "ValueSource": {
        "Values": null,
        "SharedValues": null
      },
      "CampID": 0,
      "UseDistrictTriggerType": false,
      "Trigger": null,
      "AIConfig": null,
      "AIVariableSource": null,
      "SOConfig": null,
      "StaticNPC": false,
      "OverrideLodTemplate": "WithoutLod",
      "DialogueTriggerAngle": 120,
      "DialogueGroups": [],
      "ServerInteractVerificationIDList": [],
      "IsOverrideArtModelOffset": false,
      "OverrideArtModelOffset": {
        "x": 0.0,
        "y": 0.0,
        "z": 0.0,
        "IsNaN": false,
        "IsInfinity": false,
        "IsPositiveInfinity": false,
        "IsNegativeInfinity": false,
        "magnitude": 0.0,
        "sqrMagnitude": 0.0
      },
      "DefaultIdleStateName": null,
      "DefaultBlendShapeConfigName": null,
      "BoneEmotionName": null,
      "IsOverrideAtlasEmotion": false,
      "OverrideAtlasEmotion": null,
      "DefaultLookAtMode": "LookPlayer",
      "DefaultLookAtTargetInfo": null,
      "DefaultLookAtPositionInfo": null,
      "MappingInfoID": 0,
      "SubMapID": 0,
      "OverrideTriggerSound": false,
      "SoundRange": 0.0,
      "NPCLodType": "Normal",
      "PossessionConfig": null,
      "BoardShowList": [],
      "OverrideNPCName": {
        "hash": 371857150
      },
      "OverrideNPCTitle": {
        "hash": 371857150
      },
      "DefaultStory": null,
      "FirstDialogueGroupID": 0,
      "TalkChosenType": "undefined",
      "TalkDialogGroupIDList": [],
      "DefaultAnimationType": "FreeStyle",
      "DefaultIdleFreeStyleMotionID": 313020000,
      "FreeStyleAnimGraphName": null,
      "OverrideSeriesID": 0,
      "IsMapContent": false,
      "MiniMapIconType": 0,
      "BornType": "Mission",
      "IsNeedFade": false,
      "IsInitialHidden": false,
      "InitialHiddenNodeList": [],
      "Dialog": null,
      "InteractIconType": "ChatIcon",
      "DialogueTriggerSkipFakeAvatar": true,
      "DialogueTriggerSkipSpecifiedFakeAvatarList": null,
      "OverrideBehaviorType": "None",
      "OverrideBehaviorParameter": null,
      "OverrideReplaceMaterialKeyList": null,
      "NearestTeleportMappingInfoID": 0,
      "RaidID": 0,
      "ActivityMapConditionIDList": null,
      "CameraCollisionPoint": {
        "x": 0.0,
        "y": 0.0,
        "z": 0.0,
        "IsNaN": false,
        "IsInfinity": false,
        "IsPositiveInfinity": false,
        "IsNegativeInfinity": false,
        "magnitude": 0.0,
        "sqrMagnitude": 0.0
      },
      "CameraCenterEntityList": null,
      "CameraConfig": null,
      "SFXOnLoad": null,
      "SpawnConfig": {
        "TryCapture": true,
        "CaptureDistanceTolerance": 1.5,
        "OverrideSpawn": false,
        "EntitySpawnConfig": {
          "NeedBlackIn": true,
          "BlackInDistance": 25.0,
          "NeedFadeIn": true,
          "NeedFadeOut": true
        }
      },
      "IsClientOnly": false,
      "OverrideTriggerValidGuestConfig": false,
      "TriggerValidGuest": {
        "ConfigType": "ByEntityType",
        "Npc": false,
        "NpcMonster": false,
        "LocalPlayer": true,
        "Teammember": true,
        "FakePlayer": false,
        "TargetList": null,
        "EvaluatedInstances": null
      },
      "Name": "NPC2",
      "RotY": 117.088,
      "ID": 400002,
      "PosX": -3.88,
      "PosY": -4E-06,
      "PosZ": -1.916,
      "IsDelete": false
    }
  ],
  "CrowdList": [],
  "PedestrianList": [],
  "PedestrianV2List": null,
  "AudienceList": null,
  "SmartObjectList": [],
  "CurveList": null,
  "LittleGameList": null
}